my_clicker/__init__.py
my_clicker/example.py
my_clicker-0.0.1.dist-info/METADATA
my_clicker-0.0.1.dist-info/WHEEL
my_clicker-0.0.1.dist-info/top_level.txt
my_clicker-0.0.1.dist-info/RECORD
